Char/Char.py
Char/__init__.py
Illegal/Illegal.py
Illegal/__init__.py
Int/Int16.py
Int/Int2.py
Int/Int32.py
Int/Int4.py
Int/Int64.py
Int/Int8.py
Int/__init__.py
LinkedList/__init__.py
LinkedList/linkedlist.py
Matrix/__init__.py
Matrix/matrix.py
customdatatypes-0.0.2.dist-info/LICENSE
customdatatypes-0.0.2.dist-info/METADATA
customdatatypes-0.0.2.dist-info/WHEEL
customdatatypes-0.0.2.dist-info/top_level.txt
customdatatypes-0.0.2.dist-info/RECORD
