Metadata-Version: 2.1
Name: customdatatypes
Version: 0.0.2
Summary: Custom Data Tpes
Home-page: UNKNOWN
Author: Debaditya Malakar
Author-email: debadityamalakar@outlook.com
License: UNKNOWN
Keywords: python,first package
Platform: UNKNOWN
Classifier: Development Status :: 3 - Alpha
Classifier: Intended Audience :: Education
Classifier: Programming Language :: Python :: 2
Classifier: Programming Language :: Python :: 3
Classifier: Operating System :: MacOS :: MacOS X
Classifier: Operating System :: Microsoft :: Windows
Requires-Dist: bitstring (>=4.0.1)
